{"4+DzqXFpj/z2AIwVP9lcYQ==":"background5.jpg","dMWqrKByXBwlg4JP58E4zA==":"1600x1000-towidth-100-img-1127-1600x1067.jpg","BZjr6OeMTr36HhtpXhzGCg==":"tom-1-1100x1100.jpg","D0cWJTT7ABPdDJ2Gjae6gA==":"alex-1-1100x1100.jpg","mEb+oBfBSKmByl81biO2JQ==":"bergmann-1-1100x1100.jpg","YXaOk4+rFEti03QqPukP4w==":"marielystweb-1-1100x1100.jpg","vwpIpaEZ0K8daJPfXmmPJA==":"alex-2-1100x1100.jpg","BgtUI55hcuKsLl1pieU8iA==":"mbr-1920x1121.jpg","PveiHkkpxxxvS0NQP9k+Tw==":"mbr-1920x1280.jpg","d3OyBCaNndywOWCd/iBqog==":"mbr-1-1920x1280.jpg"}